{"q+DBL6Ip/DUrNNhuYzaAOQ==":"mbr.jpg","gsjYRdHRUVZKKoL5D2DVIg==":"mbr.jpeg","Jvd/Hv+E6dzGxsxf1OSMGw==":"mbr-1.jpg","Rkh6VN1geuklqasa+Hps8w==":"mbr-2.jpg","OgtCKla7ZhzAplY/dXMFRQ==":"mbr-3.jpg","7cAX25vTViPzsEpxKtfgnw==":"mbr-4.jpg","Bzg68IuBcRh9sFO8XLZmEQ==":"mbr-5.jpg","3L8x5ialuZVROWzapuz4nA==":"mbr-6.jpg","5Yxz1Ro3xgEvJK27QZYsvA==":"mbr-1.jpeg","orRrDp0O7uYYPUWXMASTrg==":"mbr-2.jpeg","hNnJ/ah4jJ+gnKLIjKCM+Q==":"mbr-3.jpeg","8lvp9ISHPOav0iH8GHzE5A==":"mbr-596x397.jpg","b6bzUiTywy5nUlj2Gu0uRw==":"code1.jpg","Wubz4yyrDJc4jQKoX0BjwA==":"code2.jpg","BWIiynFOupEOzUSQ2lOdrg==":"mbr-4.jpg","JvcJL2HzgNJ0uLFydhK96Q==":"profile2-1076x1615.jpeg","Zn/SlYQ28oM6n1jjbcw3Dg==":"profile1-1076x1615.jpeg","Fg5v5jkvmDkCEaOcgU1Fbw==":"logo-96x96.jpeg","6jXSdP2xVBERcnsoAcG+gA==":"screenshot%20(22)-506x304.png","3UT3Z83sm2Fpct6TUJfByA==":"screenshot%20(23)-696x418.png","IJlSmcEACa+RViTns7qMMg==":"screenshot%20(24)-696x418.png","wbE7Dst+vd3N2bLcDkkJXQ==":"screenshot%20(23)-696x418.png","hM/JlVBvoW8UTs9N6CEORQ==":"screenshot%20(22)-506x304.png","m7mzpfv+wP8tRFpUsMvoCw==":"screenshot%20(22)-506x304.png","MLy4Egihuf7TTIrHar5ONA==":"screenshot%20(22)-506x304.png","IEE0sWKdosD+394jzBiqaA==":"screenshot%20(22)-506x304.png","U4fvSZ9ymc+riGEKvX10Cg==":"screenshot%20(22)-696x418.png","Q/K8XUgM6b+FFRQ5c08o9w==":"screenshot%20(24)-696x418.png","OwpClD2d5XDjPD/9VkqCWw==":"screenshot%20(24)-696x418.png"}